een/__init__.py
een/api_client.py
een/exceptions.py
een/resources/account.py
een/resources/alerts.py
een/resources/applications.py
een/resources/auditlogs.py
een/resources/available-devices.py
een/resources/bridge-settings.py
een/resources/bridges.py
een/resources/camera-settings.py
een/resources/cameras.py
een/resources/client-settings.py
een/resources/downloads.py
een/resources/editions.py
een/resources/event-metrics.py
een/resources/eventSubscriptions.py
een/resources/events.py
een/resources/exports.py
een/resources/feeds.py
een/resources/files.py
een/resources/idp-groups.py
een/resources/jobs.py
een/resources/languages.py
een/resources/layouts.py
een/resources/locations.py
een/resources/lpr-events.py
een/resources/lpr-rules.py
een/resources/lpr-vehicle-lists.py
een/resources/media-session.py
een/resources/media.py
een/resources/multicameras.py
een/resources/notifications.py
een/resources/ptz-settings.py
een/resources/ptz.py
een/resources/resource-grants.py
een/resources/roles.py
een/resources/scim-settings.py
een/resources/speaker-settings.py
een/resources/speakers.py
een/resources/sso.py
een/resources/switches.py
een/resources/tags.py
een/resources/time-zones.py
een/resources/token-generation.py
een/resources/users.py
een/resources/video-analytic-events.py
een/utils.py
eensdk_python-0.7.8.dist-info/METADATA
eensdk_python-0.7.8.dist-info/WHEEL
eensdk_python-0.7.8.dist-info/RECORD
