Metadata-Version: 2.3
Name: eensdk-python
Version: 0.7.8
Summary: A Python SDK for the Eagle Eye Networks VMS
License: MIT
Author: Darrell Malone Jr.
Author-email: dmalone@een.com
Requires-Python: >=3.11,<4.0
Classifier: License :: OSI Approved :: MIT License
Classifier: Programming Language :: Python :: 3
Classifier: Programming Language :: Python :: 3.11
Classifier: Programming Language :: Python :: 3.12
Classifier: Programming Language :: Python :: 3.13
Requires-Dist: requests (>=2.32.3,<3.0.0)
